{
    "id":  "s45111s",
    "icd10":  "S45111S",
    "name":  "Laceration of brachial artery, right side, sequela",
    "category":  "shoulder-arm-injury",
    "triage_priority":  "",
    "description":  "Laceration of brachial artery, right side, sequela",
    "red_flags":  [

                  ],
    "assess_first":  [

                     ],
    "procedures":  [

                   ],
    "drugs":  [

              ],
    "modifiers":  {
                      "pediatric":  {
                                        "note":  ""
                                    },
                      "obstetric":  {
                                        "note":  ""
                                    }
                  },
    "escalate_if":  "",
    "source":  "ICD-10-CM FY2025"
}
