{
  "id": "field-delivery",
  "name": "משלוח שדה חירום",
  "category": "obstetric",
  "skill_level": "חובש קרבי",
  "time_estimate": "משתנה -- 20+ דקות",
  "description": "ניהול אספקה ​​מזעזעת או לא מתוכננת בסביבה מחמירה.",
  "equipment": [
    "כפפות",
    "שמיכות-בד נקי",
    "כבל-מלחציים-או-עניבות",
    "מספריים",
    "נורה-מזרק"
  ],
  "steps": [
    "הנח את האם בשכיבה או שכיבה למחצה. הטיה לרוחב שמאלה מועדפת אם מחוסר הכרה (מונעת דחיסה של אבי העורקים).",
    "שליטה במשלוח הראש - תמיכה בכף היד. אל תמשוך.",
    "לאחר מסירת הראש, בדוק אם יש חבל עורף (מסביב לצוואר). אם קיים, החליקו מעל הראש. אם חזק, מהדקים וחותכים.",
    "שאבו את הפה ואז את האף עם מזרק נורה אם זמין.",
    "הנח את הלידה של הכתף הקדמית על ידי מתיחה עדינה כלפי מטה על הראש, ולאחר מכן כלפי מעלה עבור הכתף האחורית.",
    "מסירת הגוף - שימו לב לזמן המסירה.",
    "יבש וחמם את התינוק מיד. לעורר על ידי שפשוף הגב.",
    "מהדקים וחותכים את הכבל (המתן 1-2 דקות אם התינוק יציב).",
    "שלח את השליה עם מתיחה מבוקרת עדינה -- אל תכריח.",
    "יש לתת אוקסיטוצין (אם זמין) כדי למנוע דימום לאחר לידה לאחר לידה שליה.",
    "הערכת דימום לאחר לידה -- עיסוי פונדאלי, דחיסה דו-ידנית במידת הצורך.",
    "הערכת ציון אפגר ב-1 ו-5 דקות."
  ],
  "warnings": [
    "אם המסירה לא קרובה - אל תנסה. עדיף Rapid MEDEVAC.",
    "דיסטוציה של הכתף: אם הכתפיים תקועות, הפעל תמרון מקרוברט (היפרפלקס ירכיים) ולחץ סופר-פובי.",
    "דימום לאחר לידה הוא הגורם המוביל למוות אימהי שניתן למנוע - הכינו אוקסיטוצין."
  ],
  "source": "JTS Obstetric CPG / PHTLS"
}
