{
    "id":  "s82144p",
    "icd10":  "S82144P",
    "name":  "Nondisplaced bicondylar fracture of right tibia, subsequent encounter for closed fracture with malunion",
    "category":  "knee-leg-injury",
    "triage_priority":  "",
    "description":  "Nondisplaced bicondylar fracture of right tibia, subsequent encounter for closed fracture with malunion",
    "red_flags":  [

                  ],
    "assess_first":  [

                     ],
    "procedures":  [

                   ],
    "drugs":  [

              ],
    "modifiers":  {
                      "pediatric":  {
                                        "note":  ""
                                    },
                      "obstetric":  {
                                        "note":  ""
                                    }
                  },
    "escalate_if":  "",
    "source":  "ICD-10-CM FY2025"
}
