{
    "id":  "s62226b",
    "icd10":  "S62226B",
    "name":  "Nondisplaced Rolando\u0027s fracture, unspecified hand, initial encounter for open fracture",
    "category":  "wrist-hand-injury",
    "triage_priority":  "",
    "description":  "Nondisplaced Rolando\u0027s fracture, unspecified hand, initial encounter for open fracture",
    "red_flags":  [

                  ],
    "assess_first":  [

                     ],
    "procedures":  [

                   ],
    "drugs":  [

              ],
    "modifiers":  {
                      "pediatric":  {
                                        "note":  ""
                                    },
                      "obstetric":  {
                                        "note":  ""
                                    }
                  },
    "escalate_if":  "",
    "source":  "ICD-10-CM FY2025"
}