{
    "id":  "s12530k",
    "icd10":  "S12530K",
    "name":  "Unspecified traumatic displaced spondylolisthesis of sixth cervical vertebra, subsequent encounter for fracture with nonunion",
    "category":  "head-neck-injury",
    "triage_priority":  "",
    "description":  "Unspecified traumatic displaced spondylolisthesis of sixth cervical vertebra, subsequent encounter for fracture with nonunion",
    "red_flags":  [

                  ],
    "assess_first":  [

                     ],
    "procedures":  [

                   ],
    "drugs":  [

              ],
    "modifiers":  {
                      "pediatric":  {
                                        "note":  ""
                                    },
                      "obstetric":  {
                                        "note":  ""
                                    }
                  },
    "escalate_if":  "",
    "source":  "ICD-10-CM FY2025"
}
