{
    "id":  "s42156a",
    "icd10":  "S42156A",
    "name":  "Nondisplaced fracture of neck of scapula, unspecified shoulder, initial encounter for closed fracture",
    "category":  "shoulder-arm-injury",
    "triage_priority":  "",
    "description":  "Nondisplaced fracture of neck of scapula, unspecified shoulder, initial encounter for closed fracture",
    "red_flags":  [

                  ],
    "assess_first":  [

                     ],
    "procedures":  [

                   ],
    "drugs":  [

              ],
    "modifiers":  {
                      "pediatric":  {
                                        "note":  ""
                                    },
                      "obstetric":  {
                                        "note":  ""
                                    }
                  },
    "escalate_if":  "",
    "source":  "ICD-10-CM FY2025"
}
