{
    "id":  "t3992xa",
    "icd10":  "T3992XA",
    "name":  "Poisoning by unspecified nonopioid analgesic, antipyretic and antirheumatic, intentional self-harm, initial encounter",
    "category":  "burn-corrosion",
    "triage_priority":  "",
    "description":  "Poisoning by unspecified nonopioid analgesic, antipyretic and antirheumatic, intentional self-harm, initial encounter",
    "red_flags":  [

                  ],
    "assess_first":  [

                     ],
    "procedures":  [

                   ],
    "drugs":  [

              ],
    "modifiers":  {
                      "pediatric":  {
                                        "note":  ""
                                    },
                      "obstetric":  {
                                        "note":  ""
                                    }
                  },
    "escalate_if":  "",
    "source":  "ICD-10-CM FY2025"
}
