{
    "id":  "t5804xa",
    "icd10":  "T5804XA",
    "name":  "Toxic effect of carbon monoxide from motor vehicle exhaust, undetermined, initial encounter",
    "category":  "poisoning-adverse",
    "triage_priority":  "",
    "description":  "Toxic effect of carbon monoxide from motor vehicle exhaust, undetermined, initial encounter",
    "red_flags":  [

                  ],
    "assess_first":  [

                     ],
    "procedures":  [

                   ],
    "drugs":  [

              ],
    "modifiers":  {
                      "pediatric":  {
                                        "note":  ""
                                    },
                      "obstetric":  {
                                        "note":  ""
                                    }
                  },
    "escalate_if":  "",
    "source":  "ICD-10-CM FY2025"
}
