{
    "id":  "s70219a",
    "icd10":  "S70219A",
    "name":  "Abrasion, unspecified hip, initial encounter",
    "category":  "hip-thigh-injury",
    "triage_priority":  "",
    "description":  "Abrasion, unspecified hip, initial encounter",
    "red_flags":  [

                  ],
    "assess_first":  [

                     ],
    "procedures":  [

                   ],
    "drugs":  [

              ],
    "modifiers":  {
                      "pediatric":  {
                                        "note":  ""
                                    },
                      "obstetric":  {
                                        "note":  ""
                                    }
                  },
    "escalate_if":  "",
    "source":  "ICD-10-CM FY2025"
}
