{
    "id":  "s0460xs",
    "icd10":  "S0460XS",
    "name":  "Injury of acoustic nerve, unspecified side, sequela",
    "category":  "head-neck-injury",
    "triage_priority":  "",
    "description":  "Injury of acoustic nerve, unspecified side, sequela",
    "red_flags":  [

                  ],
    "assess_first":  [

                     ],
    "procedures":  [

                   ],
    "drugs":  [

              ],
    "modifiers":  {
                      "pediatric":  {
                                        "note":  ""
                                    },
                      "obstetric":  {
                                        "note":  ""
                                    }
                  },
    "escalate_if":  "",
    "source":  "ICD-10-CM FY2025"
}