{
    "id":  "s271xxd",
    "icd10":  "S271XXD",
    "name":  "Traumatic hemothorax, subsequent encounter",
    "category":  "thorax-injury",
    "triage_priority":  "",
    "description":  "Traumatic hemothorax, subsequent encounter",
    "red_flags":  [

                  ],
    "assess_first":  [

                     ],
    "procedures":  [

                   ],
    "drugs":  [

              ],
    "modifiers":  {
                      "pediatric":  {
                                        "note":  ""
                                    },
                      "obstetric":  {
                                        "note":  ""
                                    }
                  },
    "escalate_if":  "",
    "source":  "ICD-10-CM FY2025"
}