{
    "id":  "t484x4a",
    "icd10":  "T484X4A",
    "name":  "Poisoning by expectorants, undetermined, initial encounter",
    "category":  "poisoning-adverse",
    "triage_priority":  "",
    "description":  "Poisoning by expectorants, undetermined, initial encounter",
    "red_flags":  [

                  ],
    "assess_first":  [

                     ],
    "procedures":  [

                   ],
    "drugs":  [

              ],
    "modifiers":  {
                      "pediatric":  {
                                        "note":  ""
                                    },
                      "obstetric":  {
                                        "note":  ""
                                    }
                  },
    "escalate_if":  "",
    "source":  "ICD-10-CM FY2025"
}