{
    "id":  "t81509s",
    "icd10":  "T81509S",
    "name":  "Unspecified complication of foreign body accidentally left in body following unspecified procedure, sequela",
    "category":  "complications-treatment",
    "triage_priority":  "",
    "description":  "Unspecified complication of foreign body accidentally left in body following unspecified procedure, sequela",
    "red_flags":  [

                  ],
    "assess_first":  [

                     ],
    "procedures":  [

                   ],
    "drugs":  [

              ],
    "modifiers":  {
                      "pediatric":  {
                                        "note":  ""
                                    },
                      "obstetric":  {
                                        "note":  ""
                                    }
                  },
    "escalate_if":  "",
    "source":  "ICD-10-CM FY2025"
}
