{
  "id": "broselow-tape",
  "name": "د بروسلو پیډیاټریک بیړني ټیپ حواله",
  "description": "د ماشومانو د درملو اداره کولو لپاره د رنګ کوډ شوي وزن ته د خوراک حواله کله چې پیمانه شتون نلري. ماشوم د سر له پورتنۍ برخې څخه تر پښې اندازه کړئ او د رنګ بینډ سره میچ کړئ.",
  "note": "دا حواله یوازې د ESTIMATION لپاره ده. کله چې شتون ولري اصلي وزن وکاروئ.",
  "bands": [
    {
      "color": "خړ",
      "weight_kg": "3-5",
      "length_cm": "۴۶-۵۷",
      "est_age": "نوی زیږیدلی"
    },
    {
      "color": "ګلابي",
      "weight_kg": "۶-۷",
      "length_cm": "57-67",
      "est_age": "3-6 میاشتې"
    },
    {
      "color": "سور",
      "weight_kg": "۸-۹",
      "length_cm": "۶۷-۷۴",
      "est_age": "6-12 میاشتې"
    },
    {
      "color": "ارغواني",
      "weight_kg": "10-11",
      "length_cm": "74-83",
      "est_age": "12-18 میاشتې"
    },
    {
      "color": "ژیړ",
      "weight_kg": "12-14",
      "length_cm": "۸۳-۹۵",
      "est_age": "18 میاشتې - 3 کاله"
    },
    {
      "color": "سپین",
      "weight_kg": "15-18",
      "length_cm": "95-107",
      "est_age": "3-5 کاله"
    },
    {
      "color": "آبي",
      "weight_kg": "۱۹-۲۲",
      "length_cm": "107-122",
      "est_age": "5-7 کاله"
    },
    {
      "color": "نارنجي",
      "weight_kg": "24-28",
      "length_cm": "۱۲۲-۱۳۷",
      "est_age": "7-9 کاله"
    },
    {
      "color": "شین",
      "weight_kg": "30-36",
      "length_cm": "137-152",
      "est_age": "9-12 کاله"
    }
  ],
  "source": "Broselow Pediatric Emergency Reference / PALS"
}
