{
  "id": "wound-packing",
  "name": "हेमोस्टैटिक घाव पैकिंग",
  "category": "hemorrhage-control",
  "skill_level": "युद्ध-जीवनरक्षक",
  "time_estimate": "3-5 मिनट",
  "description": "रक्तस्राव को नियंत्रित करने के लिए हेमोस्टैटिक धुंध के साथ एक गैर-संपीड़ित या जंक्शन घाव की पैकिंग जहां टूर्निकेट लागू नहीं किया जा सकता है।",
  "equipment": [
    "हेमोस्टैटिक-गॉज़",
    "नाइट्राइल-दस्ताने",
    "आघात-कैंची",
    "दबाव-पट्टी"
  ],
  "steps": [
    "दस्ताने मत पहनो. आघात कैंची का उपयोग करके घाव को पूरी तरह से उजागर करें।",
    "घाव गुहा के भीतर सक्रिय रक्तस्राव स्रोत की पहचान करें।",
    "हेमोस्टैटिक धुंध खोलें और इसे अपनी उंगली से घाव में मजबूती से पैक करें, इसे सीधे रक्तस्राव स्रोत पर धकेलें।",
    "घाव की गुहा पूरी तरह भर जाने तक पैकिंग जारी रखें।",
    "कम से कम 3 मिनट के लिए अपने हाथ की एड़ी से लगातार सीधा दबाव डालें।",
    "एक बार लगाने के बाद किसी भी पैकिंग सामग्री को न हटाएं।",
    "भरे हुए घाव पर एक दबाव पट्टी लगाएं।",
    "टीसीसीसी कार्ड या मरीज के माथे पर समय अंकित करें (उदाहरण के लिए, 'पीकेडी 0145')।"
  ],
  "warnings": [
    "छाती में छेद करने वाले घावों को पैक न करें - इसके बजाय छाती सील का उपयोग करें।",
    "यदि गर्दन के घाव को पैक कर रहे हैं, तो दोनों कैरोटिड को एक साथ संपीड़ित किए बिना दबाव डालें।",
    "यदि धमनी स्रोत का संदेह हो तो 5 मिनट के भीतर पुनर्मूल्यांकन करें।"
  ],
  "follows": [
    "प्रत्यक्ष-दबाव"
  ],
  "precedes": [
    "टूर्निकेट-आवेदन"
  ],
  "modifiers": {
    "pediatric": {
      "note": "आनुपातिक रूप से कम धुंध का प्रयोग करें। शिशुओं में वक्ष संपीड़न से बचने के लिए हल्का दबाव डालें।"
    },
    "obstetric": {
      "note": "गंभीर पेट के पास गहरे या आक्रामक पैकिंग दबाव से बचें। तीव्र वृद्धि को प्राथमिकता दी जाती है."
    }
  },
  "source": "TCCC / JTS CPG CoTCCC"
}